liquipediapy/__init__.py
liquipediapy/counterstrike.py
liquipediapy/dota.py
liquipediapy/exceptions.py
liquipediapy/liquipediapy.py
liquipediapy/dota_modules/__init__.py
liquipediapy/dota_modules/player.py
liquipediapy/dota_modules/pro_circuit.py
liquipediapy/dota_modules/team.py
liquipediapy-2.0.0.dist-info/METADATA
liquipediapy-2.0.0.dist-info/RECORD
liquipediapy-2.0.0.dist-info/WHEEL
liquipediapy-2.0.0.dist-info/top_level.txt
