Metadata-Version: 2.1
Name: liquipediapy
Version: 2.0.0
Summary: api for liquipedia.net
Home-page: https://github.com/c00kie17/liquipediapy
Author: c00kie17
Author-email: anshul1708@gmail.com
License: UNKNOWN
Platform: UNKNOWN
Classifier: Programming Language :: Python :: 3
Classifier: License :: OSI Approved :: MIT License
Classifier: Operating System :: OS Independent
Requires-Dist: beautifulsoup4 (>=4.6.3)
Requires-Dist: requests (>=2.20.1)
Requires-Dist: urllib3 (>=1.23)
Requires-Dist: lxml (>=4.2.4)
